django_model_populator-0.1.0.dist-info/licenses/LICENSE
django_model_populator-0.1.0.dist-info/licenses/LICENSE.md
model_populator/__init__.py
model_populator/admin.py
model_populator/apps.py
model_populator/engine.py
model_populator/field_mappings.py
model_populator/models.py
model_populator/proxy.py
model_populator/tests.py
model_populator/views.py
model_populator/management/__init__.py
model_populator/management/commands/__init__.py
model_populator/management/commands/populate.py
model_populator/migrations/__init__.py
django_model_populator-0.1.0.dist-info/METADATA
django_model_populator-0.1.0.dist-info/WHEEL
django_model_populator-0.1.0.dist-info/top_level.txt
django_model_populator-0.1.0.dist-info/RECORD
