Metadata-Version: 2.4
Name: django-model-populator
Version: 0.1.0
Summary: A Django application for automatically populating your database with fake/dummy data
Author-email: Mathias AG <mathiasag07@gmail.com>
License: MIT
Project-URL: Homepage, https://github.com/mathiasag7/django-model-populator
Project-URL: Documentation, https://github.com/mathiasag7/django-model-populator#readme
Project-URL: Repository, https://github.com/mathiasag7/django-model-populator
Project-URL: Bug Tracker, https://github.com/mathiasag7/django-model-populator/issues
Project-URL: Changelog, https://github.com/mathiasag7/django-model-populator/blob/main/CHANGELOG.md
Keywords: django,fake,faker,dummy-data,test-data,fixtures,testing,development,database,population,model,populator
Classifier: Development Status :: 4 - Beta
Classifier: Environment :: Web Environment
Classifier: Framework :: Django
Classifier: Framework :: Django :: 3.2
Classifier: Framework :: Django :: 4.0
Classifier: Framework :: Django :: 4.1
Classifier: Framework :: Django :: 4.2
Classifier: Framework :: Django :: 5.0
Classifier: Framework :: Django :: 5.1
Classifier: Framework :: Django :: 5.2
Classifier: Intended Audience :: Developers
Classifier: License :: OSI Approved :: MIT License
Classifier: Operating System :: OS Independent
Classifier: Programming Language :: Python
Classifier: Programming Language :: Python :: 3
Classifier: Programming Language :: Python :: 3.9
Classifier: Programming Language :: Python :: 3.10
Classifier: Programming Language :: Python :: 3.11
Classifier: Programming Language :: Python :: 3.12
Classifier: Programming Language :: Python :: 3.13
Classifier: Topic :: Software Development :: Libraries :: Python Modules
Classifier: Topic :: Software Development :: Testing
Classifier: Topic :: Utilities
Requires-Python: <4.0,>=3.9
License-File: LICENSE
License-File: LICENSE.md
Requires-Dist: build>=1.3.0
Requires-Dist: django>=4.2
Requires-Dist: faker>=37.0.0
Requires-Dist: tqdm>=4.67.0
Requires-Dist: twine>=6.2.0
Provides-Extra: dev
Requires-Dist: django-extensions>=4.1; extra == "dev"
Requires-Dist: black>=25.0; extra == "dev"
Requires-Dist: pytest>=7.0; extra == "dev"
Requires-Dist: pytest-django>=4.5; extra == "dev"
Dynamic: license-file
